CHANGES.txt
COPYRIGHT.txt
LICENSE.txt
README.txt
setup.py
doc/intro.txt
doc/uppercase.ini
repoze/__init__.py
repoze.obob.egg-info/PKG-INFO
repoze.obob.egg-info/SOURCES.txt
repoze.obob.egg-info/dependency_links.txt
repoze.obob.egg-info/entry_points.txt
repoze.obob.egg-info/namespace_packages.txt
repoze.obob.egg-info/not-zip-safe
repoze.obob.egg-info/requires.txt
repoze.obob.egg-info/test_info.txt
repoze.obob.egg-info/top_level.txt
repoze/obob/__init__.py
repoze/obob/publisher.py
repoze/obob/templates/__init__.py
repoze/obob/templates/newbob_skel/sample.ini_tmpl
repoze/obob/templates/newbob_skel/setup.py_tmpl
repoze/obob/templates/newbob_skel/+package+/__init__.py
repoze/obob/templates/newbob_skel/+package+/tests.py_tmpl
repoze/obob/tests/__init__.py
repoze/obob/tests/test_publisher.py
repoze/obob/tests/test_templates.py